typer_builder/Dependencies.py
typer_builder/Dependencies_test.py
typer_builder/__init__.py
typer_builder/build_app.py
typer_builder/build_app_test.py
typer_builder/py.typed
typer_builder-0.0.11.dist-info/LICENSE
typer_builder-0.0.11.dist-info/METADATA
typer_builder-0.0.11.dist-info/WHEEL
typer_builder-0.0.11.dist-info/RECORD
