Metadata-Version: 2.1
Name: typer-builder
Version: 0.0.11
Summary: 
License: MIT
Author: Niklas Rosenstein
Author-email: rosensteinniklas@gmail.com
Requires-Python: >=3.7
Classifier: License :: OSI Approved :: MIT License
Classifier: Programming Language :: Python :: 3
Classifier: Programming Language :: Python :: 3.7
Classifier: Programming Language :: Python :: 3.8
Classifier: Programming Language :: Python :: 3.9
Classifier: Programming Language :: Python :: 3.10
Classifier: Programming Language :: Python :: 3.11
Classifier: Programming Language :: Python :: 3.12
Requires-Dist: deprecated
Requires-Dist: nr-stream (>=1.1.5,<2.0.0)
Requires-Dist: typeapi
Requires-Dist: typer
Project-URL: Bug Tracker, https://github.com/NiklasRosenstein/python-typer-builder/issues
Project-URL: Repository, https://github.com/NiklasRosenstein/typer-builder
